rajce_download.py
setup.py
rajce_download.egg-info/PKG-INFO
rajce_download.egg-info/SOURCES.txt
rajce_download.egg-info/dependency_links.txt
rajce_download.egg-info/requires.txt
rajce_download.egg-info/top_level.txt