Metadata-Version: 1.1
Name: rajce-download
Version: 1.0.0
Summary: Rajce.net photo downloader
Home-page: UNKNOWN
Author: Ondrej Sika
Author-email: ondrej@ondrejsika.com
License: MIT
Download-URL: http://github.com/sikaondrej/rajce_download
Platform: UNKNOWN
